{
  "file-explorer:new-file": [],
  "command-palette:open": [
    {
      "modifiers": [
        "Mod",
        "Shift"
      ],
      "key": "P"
    }
  ],
  "obsidian-advanced-slides:open-advanced-slides-preview": [],
  "omnisearch:show-modal-infile": [
    {
      "modifiers": [
        "Mod",
        "Shift"
      ],
      "key": "O"
    }
  ],
  "omnisearch:show-modal": [
    {
      "modifiers": [
        "Alt",
        "Mod"
      ],
      "key": "O"
    }
  ],
  "zk-prefixer": [
    {
      "modifiers": [
        "Mod"
      ],
      "key": "N"
    }
  ],
  "obsidian-completr:completr-fake-enter": [],
  "obsidian-completr:completr-fake-arrow-up": [],
  "obsidian-completr:completr-fake-arrow-down": [],
  "obsidian-completr:completr-bypass-enter-key": [],
  "obsidian-completr:completr-bypass-tab-key": [],
  "obsidian-completr:completr-insert-selected-suggestion": [],
  "obsidian-completr:completr-jump-to-next-snippet-placeholder": [],
  "obsidian-excalidraw-plugin:save": [
    {
      "modifiers": [
        "Mod",
        "Shift"
      ],
      "key": "S"
    }
  ],
  "templater-obsidian:create-99 - Meta/00 - Templates/(TEMPLATE) Unique.md": [
    {
      "modifiers": [
        "Alt"
      ],
      "key": "S"
    }
  ],
  "templater-obsidian:create-99 - Meta/00 - Templates/(TEMPLATE) Subject.md": [
    {
      "modifiers": [
        "Mod"
      ],
      "key": "U"
    }
  ],
  "templater-obsidian:create-99 - Meta/00 - Templates/(TEMPLATE) Research.md": [
    {
      "modifiers": [
        "Mod"
      ],
      "key": "R"
    }
  ]
}